{
  "module": "2",
  "lesson": "1",
  "step_number": "11",
  "step_title": "Implement methods for collaborating with peers, teachers, and faculty",
  "best_version": "# Implement Methods for Collaborating with Peers, Teachers, and Faculty\n\n## Introduction\n\nEffective collaboration is a cornerstone of success at Excel High School. Whether you're working on group projects, seeking assistance from teachers, or participating in school activities, knowing how to collaborate effectively will enhance your educational experience. In this lesson, we'll explore best practices for collaboration that will help you build meaningful connections and achieve academic success. These skills won't just serve you at Excel High School\u2014they're essential life skills that will benefit you in future educational pursuits and professional environments.\n\n## Collaboration Strategies: Best Practices\n\nLet's examine the key collaboration strategies outlined in the One Pager that will help you effectively work with peers, teachers, and faculty at Excel High School.\n\n### Communication Channels\n\nThe One Pager highlights several important communication channels available to you:\n\n- **Email**: The primary method for contacting teachers and staff. Always use your Excel High School email address for all school-related communication to ensure messages are received and properly identified.\n\n- **Learning Management System (LMS)**: Use the messaging features within your courses to ask specific questions about assignments or course content.\n\n- **Virtual Office Hours**: Take advantage of scheduled times when teachers are available for real-time assistance through video conferencing.\n\n- **Discussion Boards**: Participate actively in course discussion boards to connect with peers and demonstrate your engagement with the material.\n\n### Communication Etiquette\n\nWhen communicating with peers, teachers, and faculty, follow these best practices:\n\n- **Be Professional**: Use proper greetings, correct grammar, and appropriate language in all communications.\n\n- **Be Specific**: Clearly state your questions or concerns, providing relevant details such as course name, assignment title, or specific problem areas.\n\n- **Be Timely**: Respond to messages within 24-48 hours and plan ahead for assignment questions rather than waiting until the last minute.\n\n- **Be Respectful**: Acknowledge that responses may not be immediate, especially during weekends or after hours.\n\n### Collaborative Learning Opportunities\n\nThe One Pager emphasizes several ways to engage in collaborative learning:\n\n- **Study Groups**: Form virtual study groups with classmates to discuss course materials, review for exams, or work through challenging concepts together.\n\n- **Peer Review**: Exchange drafts of assignments with trusted peers for feedback before submission.\n\n- **Group Projects**: Contribute equitably to group work, communicate regularly with team members, and establish clear roles and deadlines.\n\n- **Academic Support Services**: Take advantage of tutoring services, writing centers, and academic advisors available through Excel High School.\n\n### Building Professional Relationships\n\nDeveloping strong relationships with peers, teachers, and faculty is essential for your academic journey:\n\n- **Introduce Yourself**: At the beginning of each course, post an introduction in discussion forums to connect with classmates and instructors.\n\n- **Participate Actively**: Regularly contribute thoughtful comments and questions in class discussions.\n\n- **Seek Feedback**: Request specific feedback on your work and use it constructively to improve.\n\n- **Express Gratitude**: Thank teachers and peers who provide assistance or valuable insights.\n\nBy implementing these collaboration strategies, you'll create a supportive network within the Excel High School community that enhances your learning experience and contributes to your academic success.\n\n## Over to You\n\n1. Which of the collaboration strategies mentioned do you think will be most beneficial to your learning style, and why?\n\n2. What challenges might you anticipate when collaborating virtually, and how could you overcome them?\n\n3. How might the collaboration skills you develop at Excel High School transfer to future educational or professional settings?",
  "explanation": "Error in comparison process: maximum recursion depth exceeded while calling a Python object. Using most structurally complete version as fallback."
}