{
  "module": "10",
  "lesson": "7",
  "step_number": "2",
  "step_title": "Sample Reflection Breakdown",
  "generations": [
    "<educational_content>\n\n# Sample Reflection Breakdown: Understanding Kindness and Empathy\n\n## Exemplar Reflection with Analysis\n\nBelow is a sample student reflection on personal growth in kindness and empathy. The margin notes explain the difference between descriptive elements (simply stating what happened) and analytical elements (examining why it matters and what was learned).\n\n---\n\n### Sample Reflection: \"My Journey with Kindness This Month\"\n\n**Situation:**\nI noticed a new student sitting alone during lunch period every day for a week. They seemed uncomfortable and didn't talk to anyone. I remembered how I felt when I was new last year.\n> *[DESCRIPTIVE: Basic observation of what happened]*\n>\n> **Question to consider:** What specific details did you notice about the situation that others might have missed?\n\n**Action:**\nI decided to invite them to sit with my friends and me. At first, they were quiet, but after introducing them to everyone and including them in our conversations, they started to open up by the end of lunch.\n> *[DESCRIPTIVE: Explains what the student did in response]*\n>\n> **Question to consider:** What alternatives did you consider before taking this action?\n\n**Internal Response:**\nInitially, I felt nervous about approaching someone new. I worried they might reject my invitation or that my friends might be annoyed. But I also felt a strong sense that it was the right thing to do because I know how isolation feels.\n> *[ANALYTICAL: Examines personal feelings and motivations]*\n>\n> **Question to consider:** How did your emotional response influence your decision-making?\n\n**Impact:**\nThe new student now regularly sits with us and has even made connections with other classmates. I've noticed they smile more and participate in class discussions. My friends commented that it was good I reached out.\n> *[DESCRIPTIVE: Observes outcomes]*\n>\n> **Question to consider:** What unexpected consequences (positive or negative) resulted from your actions?\n\n**Personal Growth:**\nThis experience helped me recognize that small acts of kindness can have significant impacts. I've become more aware of others who might feel excluded and find it easier to take the initiative now. I've learned that my initial discomfort is worth pushing through when it means helping someone else feel welcome.\n> *[ANALYTICAL: Connects experience to personal development]*\n>\n> **Question to consider:** How has this experience changed your perspective or behavior in other situations?\n\n**Deeper Understanding:**\nI realize now that empathy isn't just feeling sorry for someone\u2014it's about recognizing another person's experience and taking action. True kindness often requires stepping outside my comfort zone. I've also learned that creating inclusive spaces benefits everyone, not just the person who might feel excluded.\n> *[ANALYTICAL: Shows deeper reflection and broader insights]*\n>\n> **Question to consider:** What principles about kindness and empathy can you extract from this experience?\n\n**Future Application:**\nIn the future, I want to be more proactive about noticing when people might feel left out, not just new students but anyone who seems isolated. I plan to encourage my friends to do the same so we can create a more welcoming environment in our school.\n> *[ANALYTICAL: Applies learning to future scenarios]*\n>\n> **Question to consider:** How might you apply this learning in different contexts or challenges?\n\n---\n\n## Using This Model for Your Own Reflection\n\nWhen writing your reflection on kindness and empathy:\n\n1. Begin with **descriptive elements** that clearly explain what happened\n2. Move to **analytical elements** that explore why it matters and what you learned\n3. Use the margin questions to deepen your thinking in each section\n4. Ensure you connect your experience to personal growth in kindness and empathy\n5. Consider how your understanding has evolved and how you'll apply these insights\n\nRemember that strong reflections balance description (what happened) with analysis (why it matters and what you learned from it).\n\n</educational_content>",
    "<educational_content>\n# Sample Reflection Breakdown: Understanding Kindness and Empathy\n\n## Exemplar Reflection with Analysis\n\nBelow is a sample reflection entry that demonstrates how to effectively analyze personal experiences related to kindness and empathy. The left column contains the reflection, while the right column provides notes explaining the descriptive versus analytical components.\n\n| Sample Reflection | Analysis Notes |\n|-------------------|----------------|\n| **Last week, I helped a new student who was sitting alone at lunch.** | *Descriptive:* Simply states what happened - a basic fact without deeper analysis. |\n| **I noticed they looked uncomfortable and remembered how I felt on my first day at a new school.** | *Analytical:* Shows empathy by connecting the situation to personal experience and recognizing emotions in others. |\n| **I introduced myself and invited them to join my friends. At first, they seemed hesitant, but by the end of lunch, they were smiling and talking with everyone.** | *Descriptive:* Recounts the sequence of events and observations of what happened. |\n| **This experience made me realize how small gestures can significantly impact someone's day. I felt good afterward, but more importantly, I recognized that true kindness isn't about feeling good about myself\u2014it's about genuinely caring about others' wellbeing.** | *Analytical:* Examines the meaning behind the experience, identifies the emotional impact, and shows deeper understanding of kindness as a concept. |\n| **In the past, I might have just felt bad for the new student but not taken action. I think I've grown in my ability to notice when others need support and to take initiative rather than just having good intentions.** | *Analytical:* Identifies personal growth by comparing past and present behaviors, showing self-awareness about development of empathy. |\n| **Next time, I want to check in with them after a few days to make sure they're continuing to feel welcome, rather than assuming one interaction was enough.** | *Analytical:* Demonstrates forward thinking and ongoing commitment to kindness, showing reflection has led to actionable insights. |\n\n## Reflection Prompts for Each Section\n\nUse these questions to guide your own reflection writing:\n\n### Descriptive Components (What happened?)\n* What specific kind action did you take or witness?\n* Who was involved in the situation?\n* When and where did this occur?\n* What were the observable reactions or outcomes?\n\n### Analytical Components (What does it mean?)\n* How did this experience make you feel, and why?\n* How might others have felt in this situation?\n* What does this experience reveal about kindness or empathy?\n* How does this compare to how you might have acted in the past?\n* What personal strengths or areas for growth did you discover?\n* How has your understanding of kindness evolved?\n* What will you do differently in the future based on this experience?\n\nRemember that strong reflections balance description (what happened) with analysis (what it means). The descriptive parts provide necessary context, but the analytical components demonstrate your growth in understanding kindness and empathy. Challenge yourself to move beyond simply recounting events to exploring their deeper significance for your personal development.\n</educational_content>",
    "<educational_content>\n\n# Sample Reflection Breakdown: Understanding Kindness and Empathy\n\n## Model Reflection Entry with Analysis\n\nBelow is an exemplar reflection entry on kindness and empathy. The left column contains the student's reflection, while the right column explains whether each part is descriptive or analytical and why it matters.\n\n### Reflection Example: \"My Week of Random Acts of Kindness\"\n\n| Student Reflection | Analysis Notes |\n|-------------------|----------------|\n| This week, I challenged myself to perform at least one random act of kindness each day. On Monday, I helped an elderly neighbor carry her groceries inside when I noticed her struggling with several heavy bags. | **DESCRIPTIVE** - This part simply describes what happened (the action taken) without deeper examination. It establishes the context for reflection. |\n| I was surprised by how grateful she was for such a small gesture. It made me realize how little time it takes to make someone's day better. What I thought would be a five-minute detour turned into a meaningful connection. | **ANALYTICAL** - Here the reflection moves beyond description to examine personal reactions, unexpected outcomes, and insights gained. The writer identifies a realization about time investment versus impact. |\n| On Wednesday, I noticed a new student eating lunch alone. Remembering how I felt on my first day last year, I invited them to join my friends and me. | **DESCRIPTIVE** - Returns to describing another specific incident and action taken. |\n| This situation challenged me because I'm normally shy about approaching people I don't know. I felt anxious walking over, but pushing through that discomfort taught me something important about my own boundaries. I recognized that my momentary social anxiety was less important than someone else possibly feeling excluded all day. | **ANALYTICAL** - Excellent analysis that examines personal challenges, emotional responses, and the values clarification that occurred (weighing personal discomfort against another's needs). |\n| After a week of intentional kindness, I've noticed I'm more aware of opportunities to help others that I would have missed before. I'm beginning to understand that empathy isn't just feeling sorry for someone\u2014it's taking the time to imagine their experience and responding in a way that addresses their needs, not just what I think they need. | **ANALYTICAL** - Deep reflection that identifies growth over time, changing awareness, and a more sophisticated understanding of empathy. The writer recognizes a shift in their perspective. |\n\n## Reflection Questions to Guide Your Analysis\n\nUse these questions to help develop your own reflections on kindness and empathy:\n\n### For Descriptive Elements:\n- What specific actions did you take that demonstrated kindness?\n- Who was involved in the situation?\n- What was the context or circumstances surrounding your act of kindness?\n- How did others respond to your actions?\n\n### For Analytical Elements:\n- How did this experience make you feel before, during, and after?\n- What challenges or resistance did you encounter (either external or internal)?\n- How did this experience connect to your personal values or beliefs?\n- What surprised you about this experience?\n- How has your understanding of kindness or empathy changed?\n- What might you do differently in the future based on this experience?\n- How does this experience connect to broader themes in your life or society?\n\nRemember: Strong reflections balance description (what happened) with analysis (what it means). Description provides necessary context, but analysis demonstrates growth and learning.\n\n</educational_content>"
  ],
  "extracted_generations": [
    "# Sample Reflection Breakdown: Understanding Kindness and Empathy\n\n## Exemplar Reflection with Analysis\n\nBelow is a sample student reflection on personal growth in kindness and empathy. The margin notes explain the difference between descriptive elements (simply stating what happened) and analytical elements (examining why it matters and what was learned).\n\n---\n\n### Sample Reflection: \"My Journey with Kindness This Month\"\n\n**Situation:**\nI noticed a new student sitting alone during lunch period every day for a week. They seemed uncomfortable and didn't talk to anyone. I remembered how I felt when I was new last year.\n> *[DESCRIPTIVE: Basic observation of what happened]*\n>\n> **Question to consider:** What specific details did you notice about the situation that others might have missed?\n\n**Action:**\nI decided to invite them to sit with my friends and me. At first, they were quiet, but after introducing them to everyone and including them in our conversations, they started to open up by the end of lunch.\n> *[DESCRIPTIVE: Explains what the student did in response]*\n>\n> **Question to consider:** What alternatives did you consider before taking this action?\n\n**Internal Response:**\nInitially, I felt nervous about approaching someone new. I worried they might reject my invitation or that my friends might be annoyed. But I also felt a strong sense that it was the right thing to do because I know how isolation feels.\n> *[ANALYTICAL: Examines personal feelings and motivations]*\n>\n> **Question to consider:** How did your emotional response influence your decision-making?\n\n**Impact:**\nThe new student now regularly sits with us and has even made connections with other classmates. I've noticed they smile more and participate in class discussions. My friends commented that it was good I reached out.\n> *[DESCRIPTIVE: Observes outcomes]*\n>\n> **Question to consider:** What unexpected consequences (positive or negative) resulted from your actions?\n\n**Personal Growth:**\nThis experience helped me recognize that small acts of kindness can have significant impacts. I've become more aware of others who might feel excluded and find it easier to take the initiative now. I've learned that my initial discomfort is worth pushing through when it means helping someone else feel welcome.\n> *[ANALYTICAL: Connects experience to personal development]*\n>\n> **Question to consider:** How has this experience changed your perspective or behavior in other situations?\n\n**Deeper Understanding:**\nI realize now that empathy isn't just feeling sorry for someone\u2014it's about recognizing another person's experience and taking action. True kindness often requires stepping outside my comfort zone. I've also learned that creating inclusive spaces benefits everyone, not just the person who might feel excluded.\n> *[ANALYTICAL: Shows deeper reflection and broader insights]*\n>\n> **Question to consider:** What principles about kindness and empathy can you extract from this experience?\n\n**Future Application:**\nIn the future, I want to be more proactive about noticing when people might feel left out, not just new students but anyone who seems isolated. I plan to encourage my friends to do the same so we can create a more welcoming environment in our school.\n> *[ANALYTICAL: Applies learning to future scenarios]*\n>\n> **Question to consider:** How might you apply this learning in different contexts or challenges?\n\n---\n\n## Using This Model for Your Own Reflection\n\nWhen writing your reflection on kindness and empathy:\n\n1. Begin with **descriptive elements** that clearly explain what happened\n2. Move to **analytical elements** that explore why it matters and what you learned\n3. Use the margin questions to deepen your thinking in each section\n4. Ensure you connect your experience to personal growth in kindness and empathy\n5. Consider how your understanding has evolved and how you'll apply these insights\n\nRemember that strong reflections balance description (what happened) with analysis (why it matters and what you learned from it).",
    "# Sample Reflection Breakdown: Understanding Kindness and Empathy\n\n## Exemplar Reflection with Analysis\n\nBelow is a sample reflection entry that demonstrates how to effectively analyze personal experiences related to kindness and empathy. The left column contains the reflection, while the right column provides notes explaining the descriptive versus analytical components.\n\n| Sample Reflection | Analysis Notes |\n|-------------------|----------------|\n| **Last week, I helped a new student who was sitting alone at lunch.** | *Descriptive:* Simply states what happened - a basic fact without deeper analysis. |\n| **I noticed they looked uncomfortable and remembered how I felt on my first day at a new school.** | *Analytical:* Shows empathy by connecting the situation to personal experience and recognizing emotions in others. |\n| **I introduced myself and invited them to join my friends. At first, they seemed hesitant, but by the end of lunch, they were smiling and talking with everyone.** | *Descriptive:* Recounts the sequence of events and observations of what happened. |\n| **This experience made me realize how small gestures can significantly impact someone's day. I felt good afterward, but more importantly, I recognized that true kindness isn't about feeling good about myself\u2014it's about genuinely caring about others' wellbeing.** | *Analytical:* Examines the meaning behind the experience, identifies the emotional impact, and shows deeper understanding of kindness as a concept. |\n| **In the past, I might have just felt bad for the new student but not taken action. I think I've grown in my ability to notice when others need support and to take initiative rather than just having good intentions.** | *Analytical:* Identifies personal growth by comparing past and present behaviors, showing self-awareness about development of empathy. |\n| **Next time, I want to check in with them after a few days to make sure they're continuing to feel welcome, rather than assuming one interaction was enough.** | *Analytical:* Demonstrates forward thinking and ongoing commitment to kindness, showing reflection has led to actionable insights. |\n\n## Reflection Prompts for Each Section\n\nUse these questions to guide your own reflection writing:\n\n### Descriptive Components (What happened?)\n* What specific kind action did you take or witness?\n* Who was involved in the situation?\n* When and where did this occur?\n* What were the observable reactions or outcomes?\n\n### Analytical Components (What does it mean?)\n* How did this experience make you feel, and why?\n* How might others have felt in this situation?\n* What does this experience reveal about kindness or empathy?\n* How does this compare to how you might have acted in the past?\n* What personal strengths or areas for growth did you discover?\n* How has your understanding of kindness evolved?\n* What will you do differently in the future based on this experience?\n\nRemember that strong reflections balance description (what happened) with analysis (what it means). The descriptive parts provide necessary context, but the analytical components demonstrate your growth in understanding kindness and empathy. Challenge yourself to move beyond simply recounting events to exploring their deeper significance for your personal development.",
    "# Sample Reflection Breakdown: Understanding Kindness and Empathy\n\n## Model Reflection Entry with Analysis\n\nBelow is an exemplar reflection entry on kindness and empathy. The left column contains the student's reflection, while the right column explains whether each part is descriptive or analytical and why it matters.\n\n### Reflection Example: \"My Week of Random Acts of Kindness\"\n\n| Student Reflection | Analysis Notes |\n|-------------------|----------------|\n| This week, I challenged myself to perform at least one random act of kindness each day. On Monday, I helped an elderly neighbor carry her groceries inside when I noticed her struggling with several heavy bags. | **DESCRIPTIVE** - This part simply describes what happened (the action taken) without deeper examination. It establishes the context for reflection. |\n| I was surprised by how grateful she was for such a small gesture. It made me realize how little time it takes to make someone's day better. What I thought would be a five-minute detour turned into a meaningful connection. | **ANALYTICAL** - Here the reflection moves beyond description to examine personal reactions, unexpected outcomes, and insights gained. The writer identifies a realization about time investment versus impact. |\n| On Wednesday, I noticed a new student eating lunch alone. Remembering how I felt on my first day last year, I invited them to join my friends and me. | **DESCRIPTIVE** - Returns to describing another specific incident and action taken. |\n| This situation challenged me because I'm normally shy about approaching people I don't know. I felt anxious walking over, but pushing through that discomfort taught me something important about my own boundaries. I recognized that my momentary social anxiety was less important than someone else possibly feeling excluded all day. | **ANALYTICAL** - Excellent analysis that examines personal challenges, emotional responses, and the values clarification that occurred (weighing personal discomfort against another's needs). |\n| After a week of intentional kindness, I've noticed I'm more aware of opportunities to help others that I would have missed before. I'm beginning to understand that empathy isn't just feeling sorry for someone\u2014it's taking the time to imagine their experience and responding in a way that addresses their needs, not just what I think they need. | **ANALYTICAL** - Deep reflection that identifies growth over time, changing awareness, and a more sophisticated understanding of empathy. The writer recognizes a shift in their perspective. |\n\n## Reflection Questions to Guide Your Analysis\n\nUse these questions to help develop your own reflections on kindness and empathy:\n\n### For Descriptive Elements:\n- What specific actions did you take that demonstrated kindness?\n- Who was involved in the situation?\n- What was the context or circumstances surrounding your act of kindness?\n- How did others respond to your actions?\n\n### For Analytical Elements:\n- How did this experience make you feel before, during, and after?\n- What challenges or resistance did you encounter (either external or internal)?\n- How did this experience connect to your personal values or beliefs?\n- What surprised you about this experience?\n- How has your understanding of kindness or empathy changed?\n- What might you do differently in the future based on this experience?\n- How does this experience connect to broader themes in your life or society?\n\nRemember: Strong reflections balance description (what happened) with analysis (what it means). Description provides necessary context, but analysis demonstrates growth and learning."
  ]
}