{
  "module": "3",
  "lesson": "1",
  "step_number": "8",
  "step_title": "Responsible AI Usage Portfolio (Create)",
  "generations": [
    "<educational_content>\n# Responsible AI Usage Portfolio (Create)\n\n## LESSON INFORMATION SECTION\n\n**Module Number:** 4, Lesson 5\n\n**Lesson Title:** Creating Your Responsible AI Usage Portfolio\n\n## LEARNING COMPONENTS\n\n### Learning Objectives\n\nBy the end of this lesson, students will be able to:\n\n- Compile evidence of responsible AI usage including goal logs, scenario solutions, and reflections\n- Create a multimedia portfolio that effectively demonstrates ethical AI use\n- Evaluate their own AI usage patterns against ethical frameworks\n- Present their understanding of AI privacy, ethics, and monitoring principles\n\n## CONTENT STRUCTURE\n\n### Introduction\n\nIn today's digital landscape, the ability to use artificial intelligence tools responsibly is becoming as essential as digital literacy itself. Your journey through this course has equipped you with knowledge about AI ethics, privacy considerations, and effective monitoring practices. Now it's time to demonstrate your mastery by creating a comprehensive portfolio that showcases your understanding and application of responsible AI usage. This portfolio will not only serve as evidence of your learning but also as a personal reference guide for navigating ethical AI use in your academic and professional future. Let's explore how to compile your experiences, solutions, and reflections into a compelling multimedia presentation.\n\n### Core Concept 1: Portfolio Components and Organization\n\nA well-structured Responsible AI Usage Portfolio contains three essential components: goal logs, scenario solutions, and reflections. Your goal logs should document specific objectives you set for ethical AI use and track your progress toward meeting them. For example, you might have set a goal to properly attribute AI-generated content in your assignments or to verify AI outputs before accepting them as factual.\n\nThink of your portfolio as a professional story about your AI journey. Just as a photographer's portfolio showcases their best work and growth over time, your AI portfolio demonstrates your evolving understanding of responsible AI practices. Each component should build upon the others to create a cohesive narrative.\n\nFor organization, consider creating distinct sections with clear headings. You might structure your portfolio chronologically to show progression, or thematically around concepts like \"Privacy Protection,\" \"Ethical Decision-Making,\" and \"Critical Evaluation of AI Outputs.\" Include a table of contents and ensure each piece of evidence is dated and contextualized with brief explanations of its significance to your learning journey.\n\n### Core Concept 2: Incorporating Multimedia Elements\n\nYour portfolio should leverage various media formats to effectively communicate your understanding of responsible AI use. Consider including screenshots of AI interactions with your annotations highlighting ethical considerations, screen recordings demonstrating how you verify AI-generated information, infographics summarizing key ethical principles, or audio reflections discussing challenging scenarios.\n\nMultimedia elements function like exhibits in a museum\u2014each carefully selected to illustrate a specific aspect of your learning. For instance, a side-by-side comparison of an initial AI response and your critically evaluated, ethically improved version demonstrates your ability to apply ethical frameworks in practice.\n\nWhen creating multimedia elements, focus on quality over quantity. Each element should serve a clear purpose in demonstrating your mastery of responsible AI use. For example, rather than including dozens of screenshots, select 3-5 that best illustrate different ethical considerations you've learned to navigate. Accompany each multimedia element with a brief explanation of what it demonstrates about your understanding of responsible AI usage.\n\n### Core Concept 3: Reflection and Evidence of Growth\n\nThe reflection component of your portfolio is where you demonstrate critical thinking about your AI usage. Effective reflections go beyond describing what happened to analyze why certain approaches worked or didn't work, what you learned from challenges, and how your perspective on AI ethics has evolved.\n\nThink of your reflections as similar to a scientist's research journal\u2014documenting not just observations but interpretations, questions, and evolving hypotheses. Your reflections should demonstrate metacognition (thinking about your thinking) regarding AI use.\n\nStructure your reflections using frameworks such as:\n- What was my initial approach to this AI scenario?\n- What ethical considerations emerged?\n- How did I apply course principles to address these considerations?\n- What would I do differently next time?\n- How has this experience changed my understanding of responsible AI use?\n\nInclude specific examples that demonstrate growth. For instance, you might showcase an early scenario where you accepted AI output without verification, followed by a later scenario where you implemented a systematic approach to fact-checking and ethical evaluation. This before-and-after comparison provides compelling evidence of your developing expertise in responsible AI usage.\n\n### Core Concept 4: Presentation and Accessibility\n\nHow you present your portfolio is as important as what you include. Create a professional, accessible presentation that effectively communicates your understanding of responsible AI use. Consider using platforms like Google Sites, Microsoft Sway, Adobe Express, or even a well-organized document with hyperlinks between sections.\n\nThink of your portfolio presentation as a user interface\u2014it should be intuitive, engaging, and accessible to your audience. Just as responsible AI design considers user needs, your portfolio should be designed with your audience in mind.\n\nEnsure your portfolio is navigable with a clear structure, consistent formatting, and accessible design principles. Include alternative text for images, transcripts for audio or video content, and ensure adequate color contrast. These accessibility considerations not only make your portfolio usable by a wider audience but also demonstrate your commitment to inclusive design\u2014a key principle in responsible technology use.\n\nTest your portfolio's usability by having a peer review it. Can they easily find specific examples of your ethical AI use? Is the navigation intuitive? Does the presentation enhance rather than distract from your content? Refine your design based on this feedback before submission.\n\nRemember, your Responsible AI Usage Portfolio is both a demonstration of your learning and a personal resource for your continued ethical AI use. By thoughtfully compiling evidence, incorporating multimedia elements, reflecting deeply on your experiences, and presenting your work professionally, you'll create a compelling portfolio that showcases your mastery of responsible AI usage.\n</educational_content>",
    "<educational_content>\n# Responsible AI Usage Portfolio (Create)\n\n## LESSON INFORMATION SECTION\n\n**Module Number:** 4, Lesson 3\n\n**Lesson Title:** Creating Your Responsible AI Usage Portfolio\n\n## LEARNING COMPONENTS\n\n### Learning Objectives\n\nBy the end of this lesson, students will be able to:\n\n- Compile evidence of responsible AI usage including goal logs, scenario solutions, and reflections\n- Create a multimedia portfolio that demonstrates ethical AI implementation\n- Evaluate their own AI usage practices through structured reflection\n- Present evidence of applying AI ethics, privacy, and monitoring principles\n\n## CONTENT STRUCTURE\n\n### Introduction\n\nIn today's digital landscape, demonstrating your ability to use AI responsibly is becoming as important as the technical skills themselves. Your Responsible AI Usage Portfolio represents the culmination of your learning journey, showcasing not just what you know about ethical AI use, but how you apply these principles in practice. This portfolio will serve as tangible evidence of your commitment to responsible technology use\u2014a valuable asset for academic advancement, career opportunities, and personal development. Building on our previous explorations of AI ethics, privacy considerations, and monitoring practices, you'll now compile these elements into a cohesive presentation of your responsible AI citizenship.\n\n### Core Concept 1: Portfolio Components and Organization\n\nA comprehensive Responsible AI Usage Portfolio contains three essential components: goal logs, scenario solutions, and reflections. Goal logs document your objectives for AI use and track your progress toward responsible implementation. These should include specific, measurable targets such as \"Implement privacy-preserving techniques when using AI for data analysis\" or \"Establish personal boundaries for AI assistance in academic work.\"\n\nScenario solutions demonstrate your ability to apply ethical principles to real-world situations. For example, you might include your response to an ethical dilemma about using AI-generated content in academic work, complete with your decision-making process and justification based on ethical frameworks.\n\nReflections provide critical analysis of your AI usage patterns, challenges encountered, and growth over time. These should be honest assessments that demonstrate self-awareness and commitment to improvement. For instance, you might reflect on a time when you were tempted to over-rely on AI and how you adjusted your approach.\n\nOrganize these components chronologically or thematically, ensuring a logical flow that tells the story of your responsible AI journey. Include a table of contents and clear section headings to guide viewers through your portfolio.\n\n### Core Concept 2: Multimedia Integration and Evidence Selection\n\nYour portfolio should leverage multiple media formats to effectively showcase your responsible AI practices. Consider incorporating screenshots of AI tools with your customized privacy settings, screen recordings demonstrating how you verify AI-generated information, or audio reflections discussing ethical considerations in your decision-making process.\n\nWhen selecting evidence for inclusion, prioritize quality over quantity. Choose examples that clearly demonstrate your application of specific ethical principles or responsible practices. For instance, rather than including every AI interaction, select those that show your critical thinking about potential biases, your implementation of privacy safeguards, or your thoughtful consideration of when to use (or not use) AI assistance.\n\nCreate a visual hierarchy that guides viewers through your portfolio, using consistent formatting, color schemes, and typography. Consider this example approach: A student documented their process for fact-checking AI-generated research summaries by creating a split-screen video showing the AI output alongside their verification process using multiple credible sources. This multimedia evidence powerfully demonstrated their commitment to information integrity when using AI tools.\n\n### Core Concept 3: Reflection Framework and Growth Documentation\n\nMeaningful reflection transforms a collection of artifacts into a powerful demonstration of learning and growth. Structure your reflections using the \"What? So What? Now What?\" framework to ensure depth and actionable insights.\n\nIn the \"What?\" section, objectively describe your AI usage experiences or ethical decisions. For example: \"I established a weekly review of my AI interactions to identify potential overreliance.\"\n\nThe \"So What?\" section analyzes the significance of these experiences: \"This regular monitoring revealed that I was using AI for basic research tasks that would better develop my skills if done independently. This pattern could potentially limit my learning in certain areas.\"\n\nFinally, the \"Now What?\" section outlines your path forward: \"I've created guidelines for when to use AI assistance versus when to rely on my own abilities, focusing on using AI as an enhancement rather than a replacement for developing core competencies.\"\n\nDocument your growth by including \"before and after\" examples that demonstrate evolution in your thinking or practices. For instance, show an early interaction where you accepted AI output without verification, followed by a recent example where you implemented a robust validation process. This progression provides concrete evidence of your developing responsible AI citizenship.\n\n### Conclusion\n\nYour Responsible AI Usage Portfolio is more than just an assignment\u2014it's a powerful demonstration of your commitment to ethical technology use in an increasingly AI-integrated world. By thoughtfully compiling your goal logs, scenario solutions, and reflections into a cohesive multimedia presentation, you create a compelling narrative of your journey toward responsible AI citizenship. This portfolio serves multiple purposes: it reinforces your own learning through reflection, demonstrates your ethical awareness to others, and provides a foundation for continued growth in responsible technology use.\n\nAs you finalize your portfolio, remember that this document represents an ongoing commitment rather than a finished product. The field of AI ethics continues to evolve, and so should your approach to responsible usage. Consider how you might continue to update and expand this portfolio as you encounter new ethical challenges and develop more sophisticated approaches to addressing them.\n</educational_content>",
    "<educational_content>\n# RESPONSIBLE AI USAGE PORTFOLIO\n\n## LESSON INFORMATION SECTION\n\n**Module Number:** 4, Lesson 3\n\n**Lesson Title:** Creating Your Responsible AI Usage Portfolio\n\n## LEARNING COMPONENTS\n\n### Learning Objectives\n\nBy the end of this lesson, students will be able to:\n\n- Compile evidence of responsible AI usage including goal logs, scenario solutions, and reflections\n- Create a multimedia portfolio that effectively demonstrates ethical AI practices\n- Evaluate their own AI usage patterns and identify areas for improvement\n- Present their learning journey in a cohesive, professional format\n\n## CONTENT STRUCTURE\n\n### Introduction\n\nIn today's digital landscape, the ability to use artificial intelligence tools responsibly and ethically is becoming as essential as digital literacy itself. Throughout this course, you've explored various aspects of AI ethics, privacy considerations, and responsible usage patterns. Now it's time to bring all that learning together in a tangible way. Your Responsible AI Usage Portfolio will serve as both evidence of your learning journey and a professional showcase of your commitment to ethical AI practices. This portfolio isn't just an academic exercise\u2014it's a real-world demonstration of skills increasingly valued by employers, educational institutions, and society at large.\n\n### Core Concept 1: Portfolio Components and Evidence Collection\n\nA comprehensive Responsible AI Usage Portfolio should include diverse evidence types that showcase your understanding and application of responsible AI principles. The three primary components are goal logs, scenario solutions, and reflections.\n\n**Goal logs** document your personal journey of AI tool usage and the specific objectives you set for yourself. These should include:\n- Clear, measurable goals related to ethical AI use\n- Documentation of steps taken to achieve these goals\n- Progress tracking with timestamps\n- Challenges encountered and how you addressed them\n\n**Scenario solutions** demonstrate your ability to apply ethical principles to real-world situations. Include:\n- Your responses to the ethical dilemmas presented in class\n- Step-by-step documentation of your decision-making process\n- Citations of relevant ethical frameworks that guided your decisions\n- Alternative approaches you considered and why you made your final choice\n\n**Reflections** provide deeper insight into your learning and personal growth. These should:\n- Connect theoretical concepts to practical applications\n- Evaluate the effectiveness of your approaches\n- Identify areas for continued growth\n- Demonstrate critical thinking about AI's broader societal impacts\n\nWhen collecting your evidence, be thorough but selective. Choose examples that best demonstrate your growth and understanding rather than including everything possible.\n\n### Core Concept 2: Creating a Multimedia Presentation\n\nYour portfolio should leverage different media formats to create an engaging and comprehensive presentation of your learning. This multimedia approach allows you to showcase your technical skills while making your portfolio more accessible and impactful.\n\nBegin by selecting an appropriate platform for your portfolio. Options include:\n- Digital presentation tools (PowerPoint, Google Slides)\n- Website builders (WordPress, Wix, Google Sites)\n- Digital portfolio platforms (Seesaw, Portfolium)\n- PDF compilations with embedded media\n\nRegardless of your chosen platform, incorporate these multimedia elements:\n- **Screenshots** of your AI tool usage with annotations explaining ethical considerations\n- **Video demonstrations** of you applying responsible AI practices\n- **Infographics** summarizing key ethical principles or decision frameworks\n- **Audio reflections** providing personal insights on your learning journey\n- **Interactive elements** such as quizzes or decision trees demonstrating ethical decision-making\n\nThe most effective multimedia portfolios maintain a consistent visual identity while using different media types to highlight different aspects of your learning. Consider creating a style guide for yourself that includes consistent color schemes, fonts, and formatting to give your portfolio a professional appearance.\n\n### Core Concept 3: Demonstrating Growth and Ethical Understanding\n\nThe ultimate purpose of your portfolio is to demonstrate your growth in understanding and applying ethical AI principles. This means organizing your evidence to show progression over time and connecting your practices to broader ethical frameworks.\n\nStructure your portfolio to show your development journey:\n- Begin with an introduction that outlines your initial understanding and goals\n- Organize content chronologically or thematically to highlight progression\n- Include \"before and after\" examples showing how your practices evolved\n- Conclude with forward-looking goals and commitments\n\nThroughout your portfolio, explicitly connect your practices to ethical principles:\n- Reference specific ethical frameworks (utilitarianism, deontology, virtue ethics, etc.)\n- Discuss how you've applied concepts like privacy, transparency, and fairness\n- Analyze potential biases in AI tools and how you've worked to mitigate them\n- Consider the societal implications of AI technologies you've used\n\nInclude a self-assessment section that honestly evaluates:\n- Areas where you've demonstrated mastery\n- Skills that still require development\n- Specific actions you'll take to continue improving\n- How you plan to stay current with evolving AI ethics standards\n\nYour portfolio should demonstrate not just what you've learned but how you'll continue to apply ethical AI practices in future academic, professional, and personal contexts.\n\n### Conclusion\n\nYour Responsible AI Usage Portfolio represents more than just the completion of a course requirement\u2014it's a tangible demonstration of your commitment to using powerful technologies in ways that benefit both yourself and society. By thoughtfully compiling your goal logs, scenario solutions, and reflections into a multimedia presentation, you're creating a valuable resource that can be shared with future employers, educators, or collaborators. Remember that responsible AI usage is an ongoing journey rather than a destination. Your portfolio should reflect not just what you've accomplished, but your readiness to continue learning and adapting as AI technologies and ethical standards evolve.\n</educational_content>"
  ],
  "extracted_generations": [
    "# Responsible AI Usage Portfolio (Create)\n\n## LESSON INFORMATION SECTION\n\n**Module Number:** 4, Lesson 5\n\n**Lesson Title:** Creating Your Responsible AI Usage Portfolio\n\n## LEARNING COMPONENTS\n\n### Learning Objectives\n\nBy the end of this lesson, students will be able to:\n\n- Compile evidence of responsible AI usage including goal logs, scenario solutions, and reflections\n- Create a multimedia portfolio that effectively demonstrates ethical AI use\n- Evaluate their own AI usage patterns against ethical frameworks\n- Present their understanding of AI privacy, ethics, and monitoring principles\n\n## CONTENT STRUCTURE\n\n### Introduction\n\nIn today's digital landscape, the ability to use artificial intelligence tools responsibly is becoming as essential as digital literacy itself. Your journey through this course has equipped you with knowledge about AI ethics, privacy considerations, and effective monitoring practices. Now it's time to demonstrate your mastery by creating a comprehensive portfolio that showcases your understanding and application of responsible AI usage. This portfolio will not only serve as evidence of your learning but also as a personal reference guide for navigating ethical AI use in your academic and professional future. Let's explore how to compile your experiences, solutions, and reflections into a compelling multimedia presentation.\n\n### Core Concept 1: Portfolio Components and Organization\n\nA well-structured Responsible AI Usage Portfolio contains three essential components: goal logs, scenario solutions, and reflections. Your goal logs should document specific objectives you set for ethical AI use and track your progress toward meeting them. For example, you might have set a goal to properly attribute AI-generated content in your assignments or to verify AI outputs before accepting them as factual.\n\nThink of your portfolio as a professional story about your AI journey. Just as a photographer's portfolio showcases their best work and growth over time, your AI portfolio demonstrates your evolving understanding of responsible AI practices. Each component should build upon the others to create a cohesive narrative.\n\nFor organization, consider creating distinct sections with clear headings. You might structure your portfolio chronologically to show progression, or thematically around concepts like \"Privacy Protection,\" \"Ethical Decision-Making,\" and \"Critical Evaluation of AI Outputs.\" Include a table of contents and ensure each piece of evidence is dated and contextualized with brief explanations of its significance to your learning journey.\n\n### Core Concept 2: Incorporating Multimedia Elements\n\nYour portfolio should leverage various media formats to effectively communicate your understanding of responsible AI use. Consider including screenshots of AI interactions with your annotations highlighting ethical considerations, screen recordings demonstrating how you verify AI-generated information, infographics summarizing key ethical principles, or audio reflections discussing challenging scenarios.\n\nMultimedia elements function like exhibits in a museum\u2014each carefully selected to illustrate a specific aspect of your learning. For instance, a side-by-side comparison of an initial AI response and your critically evaluated, ethically improved version demonstrates your ability to apply ethical frameworks in practice.\n\nWhen creating multimedia elements, focus on quality over quantity. Each element should serve a clear purpose in demonstrating your mastery of responsible AI use. For example, rather than including dozens of screenshots, select 3-5 that best illustrate different ethical considerations you've learned to navigate. Accompany each multimedia element with a brief explanation of what it demonstrates about your understanding of responsible AI usage.\n\n### Core Concept 3: Reflection and Evidence of Growth\n\nThe reflection component of your portfolio is where you demonstrate critical thinking about your AI usage. Effective reflections go beyond describing what happened to analyze why certain approaches worked or didn't work, what you learned from challenges, and how your perspective on AI ethics has evolved.\n\nThink of your reflections as similar to a scientist's research journal\u2014documenting not just observations but interpretations, questions, and evolving hypotheses. Your reflections should demonstrate metacognition (thinking about your thinking) regarding AI use.\n\nStructure your reflections using frameworks such as:\n- What was my initial approach to this AI scenario?\n- What ethical considerations emerged?\n- How did I apply course principles to address these considerations?\n- What would I do differently next time?\n- How has this experience changed my understanding of responsible AI use?\n\nInclude specific examples that demonstrate growth. For instance, you might showcase an early scenario where you accepted AI output without verification, followed by a later scenario where you implemented a systematic approach to fact-checking and ethical evaluation. This before-and-after comparison provides compelling evidence of your developing expertise in responsible AI usage.\n\n### Core Concept 4: Presentation and Accessibility\n\nHow you present your portfolio is as important as what you include. Create a professional, accessible presentation that effectively communicates your understanding of responsible AI use. Consider using platforms like Google Sites, Microsoft Sway, Adobe Express, or even a well-organized document with hyperlinks between sections.\n\nThink of your portfolio presentation as a user interface\u2014it should be intuitive, engaging, and accessible to your audience. Just as responsible AI design considers user needs, your portfolio should be designed with your audience in mind.\n\nEnsure your portfolio is navigable with a clear structure, consistent formatting, and accessible design principles. Include alternative text for images, transcripts for audio or video content, and ensure adequate color contrast. These accessibility considerations not only make your portfolio usable by a wider audience but also demonstrate your commitment to inclusive design\u2014a key principle in responsible technology use.\n\nTest your portfolio's usability by having a peer review it. Can they easily find specific examples of your ethical AI use? Is the navigation intuitive? Does the presentation enhance rather than distract from your content? Refine your design based on this feedback before submission.\n\nRemember, your Responsible AI Usage Portfolio is both a demonstration of your learning and a personal resource for your continued ethical AI use. By thoughtfully compiling evidence, incorporating multimedia elements, reflecting deeply on your experiences, and presenting your work professionally, you'll create a compelling portfolio that showcases your mastery of responsible AI usage.",
    "# Responsible AI Usage Portfolio (Create)\n\n## LESSON INFORMATION SECTION\n\n**Module Number:** 4, Lesson 3\n\n**Lesson Title:** Creating Your Responsible AI Usage Portfolio\n\n## LEARNING COMPONENTS\n\n### Learning Objectives\n\nBy the end of this lesson, students will be able to:\n\n- Compile evidence of responsible AI usage including goal logs, scenario solutions, and reflections\n- Create a multimedia portfolio that demonstrates ethical AI implementation\n- Evaluate their own AI usage practices through structured reflection\n- Present evidence of applying AI ethics, privacy, and monitoring principles\n\n## CONTENT STRUCTURE\n\n### Introduction\n\nIn today's digital landscape, demonstrating your ability to use AI responsibly is becoming as important as the technical skills themselves. Your Responsible AI Usage Portfolio represents the culmination of your learning journey, showcasing not just what you know about ethical AI use, but how you apply these principles in practice. This portfolio will serve as tangible evidence of your commitment to responsible technology use\u2014a valuable asset for academic advancement, career opportunities, and personal development. Building on our previous explorations of AI ethics, privacy considerations, and monitoring practices, you'll now compile these elements into a cohesive presentation of your responsible AI citizenship.\n\n### Core Concept 1: Portfolio Components and Organization\n\nA comprehensive Responsible AI Usage Portfolio contains three essential components: goal logs, scenario solutions, and reflections. Goal logs document your objectives for AI use and track your progress toward responsible implementation. These should include specific, measurable targets such as \"Implement privacy-preserving techniques when using AI for data analysis\" or \"Establish personal boundaries for AI assistance in academic work.\"\n\nScenario solutions demonstrate your ability to apply ethical principles to real-world situations. For example, you might include your response to an ethical dilemma about using AI-generated content in academic work, complete with your decision-making process and justification based on ethical frameworks.\n\nReflections provide critical analysis of your AI usage patterns, challenges encountered, and growth over time. These should be honest assessments that demonstrate self-awareness and commitment to improvement. For instance, you might reflect on a time when you were tempted to over-rely on AI and how you adjusted your approach.\n\nOrganize these components chronologically or thematically, ensuring a logical flow that tells the story of your responsible AI journey. Include a table of contents and clear section headings to guide viewers through your portfolio.\n\n### Core Concept 2: Multimedia Integration and Evidence Selection\n\nYour portfolio should leverage multiple media formats to effectively showcase your responsible AI practices. Consider incorporating screenshots of AI tools with your customized privacy settings, screen recordings demonstrating how you verify AI-generated information, or audio reflections discussing ethical considerations in your decision-making process.\n\nWhen selecting evidence for inclusion, prioritize quality over quantity. Choose examples that clearly demonstrate your application of specific ethical principles or responsible practices. For instance, rather than including every AI interaction, select those that show your critical thinking about potential biases, your implementation of privacy safeguards, or your thoughtful consideration of when to use (or not use) AI assistance.\n\nCreate a visual hierarchy that guides viewers through your portfolio, using consistent formatting, color schemes, and typography. Consider this example approach: A student documented their process for fact-checking AI-generated research summaries by creating a split-screen video showing the AI output alongside their verification process using multiple credible sources. This multimedia evidence powerfully demonstrated their commitment to information integrity when using AI tools.\n\n### Core Concept 3: Reflection Framework and Growth Documentation\n\nMeaningful reflection transforms a collection of artifacts into a powerful demonstration of learning and growth. Structure your reflections using the \"What? So What? Now What?\" framework to ensure depth and actionable insights.\n\nIn the \"What?\" section, objectively describe your AI usage experiences or ethical decisions. For example: \"I established a weekly review of my AI interactions to identify potential overreliance.\"\n\nThe \"So What?\" section analyzes the significance of these experiences: \"This regular monitoring revealed that I was using AI for basic research tasks that would better develop my skills if done independently. This pattern could potentially limit my learning in certain areas.\"\n\nFinally, the \"Now What?\" section outlines your path forward: \"I've created guidelines for when to use AI assistance versus when to rely on my own abilities, focusing on using AI as an enhancement rather than a replacement for developing core competencies.\"\n\nDocument your growth by including \"before and after\" examples that demonstrate evolution in your thinking or practices. For instance, show an early interaction where you accepted AI output without verification, followed by a recent example where you implemented a robust validation process. This progression provides concrete evidence of your developing responsible AI citizenship.\n\n### Conclusion\n\nYour Responsible AI Usage Portfolio is more than just an assignment\u2014it's a powerful demonstration of your commitment to ethical technology use in an increasingly AI-integrated world. By thoughtfully compiling your goal logs, scenario solutions, and reflections into a cohesive multimedia presentation, you create a compelling narrative of your journey toward responsible AI citizenship. This portfolio serves multiple purposes: it reinforces your own learning through reflection, demonstrates your ethical awareness to others, and provides a foundation for continued growth in responsible technology use.\n\nAs you finalize your portfolio, remember that this document represents an ongoing commitment rather than a finished product. The field of AI ethics continues to evolve, and so should your approach to responsible usage. Consider how you might continue to update and expand this portfolio as you encounter new ethical challenges and develop more sophisticated approaches to addressing them.",
    "# RESPONSIBLE AI USAGE PORTFOLIO\n\n## LESSON INFORMATION SECTION\n\n**Module Number:** 4, Lesson 3\n\n**Lesson Title:** Creating Your Responsible AI Usage Portfolio\n\n## LEARNING COMPONENTS\n\n### Learning Objectives\n\nBy the end of this lesson, students will be able to:\n\n- Compile evidence of responsible AI usage including goal logs, scenario solutions, and reflections\n- Create a multimedia portfolio that effectively demonstrates ethical AI practices\n- Evaluate their own AI usage patterns and identify areas for improvement\n- Present their learning journey in a cohesive, professional format\n\n## CONTENT STRUCTURE\n\n### Introduction\n\nIn today's digital landscape, the ability to use artificial intelligence tools responsibly and ethically is becoming as essential as digital literacy itself. Throughout this course, you've explored various aspects of AI ethics, privacy considerations, and responsible usage patterns. Now it's time to bring all that learning together in a tangible way. Your Responsible AI Usage Portfolio will serve as both evidence of your learning journey and a professional showcase of your commitment to ethical AI practices. This portfolio isn't just an academic exercise\u2014it's a real-world demonstration of skills increasingly valued by employers, educational institutions, and society at large.\n\n### Core Concept 1: Portfolio Components and Evidence Collection\n\nA comprehensive Responsible AI Usage Portfolio should include diverse evidence types that showcase your understanding and application of responsible AI principles. The three primary components are goal logs, scenario solutions, and reflections.\n\n**Goal logs** document your personal journey of AI tool usage and the specific objectives you set for yourself. These should include:\n- Clear, measurable goals related to ethical AI use\n- Documentation of steps taken to achieve these goals\n- Progress tracking with timestamps\n- Challenges encountered and how you addressed them\n\n**Scenario solutions** demonstrate your ability to apply ethical principles to real-world situations. Include:\n- Your responses to the ethical dilemmas presented in class\n- Step-by-step documentation of your decision-making process\n- Citations of relevant ethical frameworks that guided your decisions\n- Alternative approaches you considered and why you made your final choice\n\n**Reflections** provide deeper insight into your learning and personal growth. These should:\n- Connect theoretical concepts to practical applications\n- Evaluate the effectiveness of your approaches\n- Identify areas for continued growth\n- Demonstrate critical thinking about AI's broader societal impacts\n\nWhen collecting your evidence, be thorough but selective. Choose examples that best demonstrate your growth and understanding rather than including everything possible.\n\n### Core Concept 2: Creating a Multimedia Presentation\n\nYour portfolio should leverage different media formats to create an engaging and comprehensive presentation of your learning. This multimedia approach allows you to showcase your technical skills while making your portfolio more accessible and impactful.\n\nBegin by selecting an appropriate platform for your portfolio. Options include:\n- Digital presentation tools (PowerPoint, Google Slides)\n- Website builders (WordPress, Wix, Google Sites)\n- Digital portfolio platforms (Seesaw, Portfolium)\n- PDF compilations with embedded media\n\nRegardless of your chosen platform, incorporate these multimedia elements:\n- **Screenshots** of your AI tool usage with annotations explaining ethical considerations\n- **Video demonstrations** of you applying responsible AI practices\n- **Infographics** summarizing key ethical principles or decision frameworks\n- **Audio reflections** providing personal insights on your learning journey\n- **Interactive elements** such as quizzes or decision trees demonstrating ethical decision-making\n\nThe most effective multimedia portfolios maintain a consistent visual identity while using different media types to highlight different aspects of your learning. Consider creating a style guide for yourself that includes consistent color schemes, fonts, and formatting to give your portfolio a professional appearance.\n\n### Core Concept 3: Demonstrating Growth and Ethical Understanding\n\nThe ultimate purpose of your portfolio is to demonstrate your growth in understanding and applying ethical AI principles. This means organizing your evidence to show progression over time and connecting your practices to broader ethical frameworks.\n\nStructure your portfolio to show your development journey:\n- Begin with an introduction that outlines your initial understanding and goals\n- Organize content chronologically or thematically to highlight progression\n- Include \"before and after\" examples showing how your practices evolved\n- Conclude with forward-looking goals and commitments\n\nThroughout your portfolio, explicitly connect your practices to ethical principles:\n- Reference specific ethical frameworks (utilitarianism, deontology, virtue ethics, etc.)\n- Discuss how you've applied concepts like privacy, transparency, and fairness\n- Analyze potential biases in AI tools and how you've worked to mitigate them\n- Consider the societal implications of AI technologies you've used\n\nInclude a self-assessment section that honestly evaluates:\n- Areas where you've demonstrated mastery\n- Skills that still require development\n- Specific actions you'll take to continue improving\n- How you plan to stay current with evolving AI ethics standards\n\nYour portfolio should demonstrate not just what you've learned but how you'll continue to apply ethical AI practices in future academic, professional, and personal contexts.\n\n### Conclusion\n\nYour Responsible AI Usage Portfolio represents more than just the completion of a course requirement\u2014it's a tangible demonstration of your commitment to using powerful technologies in ways that benefit both yourself and society. By thoughtfully compiling your goal logs, scenario solutions, and reflections into a multimedia presentation, you're creating a valuable resource that can be shared with future employers, educators, or collaborators. Remember that responsible AI usage is an ongoing journey rather than a destination. Your portfolio should reflect not just what you've accomplished, but your readiness to continue learning and adapting as AI technologies and ethical standards evolve."
  ]
}