<?xml version="1.0"?>
<!-- Note: This script may not meet all quality guidelines. Please review carefully. -->
<speak version="1.0" xmlns="http://www.w3.org/2001/10/synthesis" xmlns:mstts="https://www.w3.org/2001/mstts" xml:lang="en-US">
<voice name="en-US-Andrew:DragonHDLatestNeural" parameters="temperature=0.25">
<p>Hi there! Glad we’re talking about animal-inspired robots today. I really enjoy explaining how robots use different parts to copy the way animals move. My job is to show how everything fits together, step by step. We’ll look at legs, sensors, and programming. It’s like building a robot puzzle!</p>
</voice>

<voice name="en-US-Andrew2:DragonHDLatestNeural" parameters="temperature=0.6">
<p>Hey! I’m excited too. I like seeing how robots are used in real places—like search and rescue, or exploring underwater. I think students will find it cool that robots can crawl, climb, and even swim like animals. I’ll share some fun examples as we go. Let’s start with insect robots. Why do engineers copy insects so much?</p>
</voice>

<voice name="en-US-Andrew:DragonHDLatestNeural" parameters="temperature=0.25">
<p>Good question. Insects are small, but they’re really good at moving over rough ground. They have six or more legs. This keeps them balanced. Each leg moves in a certain order, so they never fall over. Take the RHex robot. It has six curved legs, like a cockroach. The robot moves each leg one after another, just like the insect. This lets it walk on sand, climb rocks, or even go up stairs.</p>
</voice>

<voice name="en-US-Andrew2:DragonHDLatestNeural" parameters="temperature=0.6">
<p>That’s neat! So, if a robot loses balance, does it just fall over?</p>
</voice>

<voice name="en-US-Andrew:DragonHDLatestNeural" parameters="temperature=0.25">
<p>Not usually. Because of the way the legs move, there are always at least three legs touching the ground. That’s like standing on a tripod—very stable. Plus, some robots have sensors that act like your skin or eyes. If the robot tips, the sensors tell it to adjust.</p>
</voice>

<voice name="en-US-Andrew2:DragonHDLatestNeural" parameters="temperature=0.6">
<p>Oh, so the sensors are like its sense of touch and balance? That reminds me of RoboBee, the tiny flying robot. It’s smaller than a paperclip! It flaps its wings really fast, like a real bee. Why not just use tiny propellers?</p>
</voice>

<voice name="en-US-Andrew:DragonHDLatestNeural" parameters="temperature=0.25">
<p>Wings work better at that size. When things get really small, moving air with wings is more efficient than spinning propellers. Also, flapping wings give better control in the air, especially in tight spaces. Engineers studied how bees flap their wings and copied that pattern for RoboBee.</p>
</voice>

<voice name="en-US-Andrew2:DragonHDLatestNeural" parameters="temperature=0.6">
<p>Cool! So, these insect robots help in places people can’t go, like after earthquakes?</p>
</voice>

<voice name="en-US-Andrew:DragonHDLatestNeural" parameters="temperature=0.25">
<p>Exactly. If a building falls, it can be dangerous for people to look for survivors. Small robots inspired by insects can crawl through cracks and tight spots. Their size and movement keep them from getting stuck or tipping over.</p>
</voice>

<voice name="en-US-Andrew2:DragonHDLatestNeural" parameters="temperature=0.6">
<p>That makes sense. Let’s talk about bigger animals. I’ve seen videos of the Spot robot dog, and it’s amazing how it can walk, climb stairs, and even keep from falling when someone pushes it. How does it do that?</p>
</voice>

<voice name="en-US-Andrew:DragonHDLatestNeural" parameters="temperature=0.25">
<p>Spot copies how real dogs walk. It has four legs. Each leg can move in different directions. There are sensors in each foot to feel the ground. The robot uses a computer program to decide how to move each leg, based on what it senses. If Spot steps on something uneven, it shifts its weight, just like a dog would.</p>
</voice>

<voice name="en-US-Andrew2:DragonHDLatestNeural" parameters="temperature=0.6">
<p>So, it’s not just about having legs, but also about knowing how and when to move them. What about snake robots? I read that they can fit into pipes or climb poles. How do they work?</p>
</voice>

<voice name="en-US-Andrew:DragonHDLatestNeural" parameters="temperature=0.25">
<p>Snake robots are made of many connected pieces, called segments. Each segment can move a little. The robot can bend and twist its body, just like a snake. There are several ways snakes move, like side-winding or concertina motion. Engineers program the robot to copy those patterns. That way, it can slither through tight spaces or wrap around objects to climb.</p>
</voice>

<voice name="en-US-Andrew2:DragonHDLatestNeural" parameters="temperature=0.6">
<p>That’s awesome! I can see why they use snake robots to check inside pipes or explore caves. But wait, do these robots ever get stuck?</p>
</voice>

<voice name="en-US-Andrew:DragonHDLatestNeural" parameters="temperature=0.25">
<p>Sometimes, yes. If the robot’s sensors don’t detect an obstacle, it might try to squeeze through a space that’s too small. That’s why it’s important to have good sensors and smart programming. The robot has to feel its way through, just like a real snake uses its sense of touch.</p>
</voice>

<voice name="en-US-Andrew2:DragonHDLatestNeural" parameters="temperature=0.6">
<p>Speaking of sensors, I heard about robots that can change how they move based on what’s around them. Like, if they bump into something, they turn instead of just pushing forward. How do they know what to do?</p>
</voice>

<voice name="en-US-Andrew:DragonHDLatestNeural" parameters="temperature=0.25">
<p>That’s where programming comes in. Robots use commands like move_forward or turn_left. But they also use “if-then” rules. For example, “if you hit an obstacle, then turn right.” Sensors tell the robot what’s happening, and the program decides what to do. It’s like playing a video game: if you see a wall, you turn your character.</p>
</voice>

<voice name="en-US-Andrew2:DragonHDLatestNeural" parameters="temperature=0.6">
<p>Great example! That’s like a robot vacuum—when it hits a wall, it turns and keeps cleaning. Or a line-following robot in school competitions. I see how programming and sensors work together. But what about flying and swimming robots? How do they copy birds or fish?</p>
</voice>

<voice name="en-US-Andrew:DragonHDLatestNeural" parameters="temperature=0.25">
<p>For flying, robots like SmartBird copy the way birds flap their wings. The wings change shape as they move, so the robot can take off, fly, and land smoothly. It’s not just up-and-down; the wings twist and bend, just like real bird wings. This makes flying more efficient and helps with turning and landing.</p>
</voice>

<voice name="en-US-Andrew2:DragonHDLatestNeural" parameters="temperature=0.6">
<p>I saw a video of SmartBird. It really looks like a seagull! And underwater, there’s the robotic fish from MIT. Instead of spinning propellers, it waves its body side to side, like a real fish. That makes it quieter and less scary for real fish, so it can study marine life better.</p>
</voice>

<voice name="en-US-Andrew:DragonHDLatestNeural" parameters="temperature=0.25">
<p>Right. Moving like a fish uses less energy, too. And there are robots that swim like manta rays or even use jet propulsion like squids. Engineers watch how these animals move, then build robots that copy their motion. Sometimes, this leads to new ideas that regular engineering wouldn’t think of.</p>
</voice>

<voice name="en-US-Andrew2:DragonHDLatestNeural" parameters="temperature=0.6">
<p>That reminds me of the Stickybot, which climbs up glass using gecko-like feet. And Pleurobot, which walks and swims like a salamander. I think students would like to know—how do engineers figure out what animal to copy for a robot?</p>
</voice>

<voice name="en-US-Andrew:DragonHDLatestNeural" parameters="temperature=0.25">
<p>They look at the problem first. For rough ground, they study insects. For tight spaces, they study snakes. For climbing, they look at geckos. They watch videos, use slow-motion cameras, and sometimes even scan animal skeletons. Then, they try to build the same movement with motors, joints, and sensors.</p>
</voice>

<voice name="en-US-Andrew2:DragonHDLatestNeural" parameters="temperature=0.6">
<p>That’s a smart way to problem-solve! But sometimes, I wonder—do robots always have to copy animals? Can’t engineers invent their own ways to move?</p>
</voice>

<voice name="en-US-Andrew:DragonHDLatestNeural" parameters="temperature=0.25">
<p>[pause] That’s a fair question. Sometimes engineers do invent new ways. But animals have spent millions of years getting really good at moving in their environments. Copying nature can save time and lead to better results. Still, you’re right—sometimes a new idea works best, especially if there’s no good animal example.</p>
</voice>

<voice name="en-US-Andrew2:DragonHDLatestNeural" parameters="temperature=0.6">
<p>Thanks for clearing that up! I guess it’s about using the best idea for the job, whether it’s from nature or not.</p>
</voice>

<voice name="en-US-Andrew:DragonHDLatestNeural" parameters="temperature=0.25">
<p>Exactly.</p>
</voice>

<voice name="en-US-Andrew2:DragonHDLatestNeural" parameters="temperature=0.6">
<p>Before we wrap up, what’s one thing you want students to remember about animal-inspired robots?</p>
</voice>

<voice name="en-US-Andrew:DragonHDLatestNeural" parameters="temperature=0.25">
<p>I’d say this: Robots are like puzzles made of parts that work together—motors, sensors, and programs. By copying animals, engineers find smart ways to solve tough problems. But it’s not magic; it’s careful study and building, step by step.</p>
</voice>

<voice name="en-US-Andrew2:DragonHDLatestNeural" parameters="temperature=0.6">
<p>I agree. I hope students see that robots aren’t just science fiction. They solve real problems, from searching for people after disasters to exploring the ocean. Maybe you’ll invent the next animal-inspired robot! Just keep asking questions and looking for clever ideas in nature.</p>
</voice>

</speak>